sfacts/__init__.py
sfacts/__main__.py
sfacts/data.py
sfacts/estimation.py
sfacts/evaluation.py
sfacts/logging_util.py
sfacts/math.py
sfacts/model.py
sfacts/pandas_util.py
sfacts/plot.py
sfacts/pyro_util.py
sfacts/unifrac.py
sfacts/workflow.py
sfacts/app/__init__.py
sfacts/app/components.py
sfacts/model_zoo/__init__.py
sfacts/model_zoo/components.py
sfacts/model_zoo/model1.py
sfacts/model_zoo/model2.py
sfacts/model_zoo/model3.py
sfacts/model_zoo/model4.py
sfacts/model_zoo/model5.py
sfacts/model_zoo/model6.py
sfacts/model_zoo/model7.py
sfacts/model_zoo/simulation0.py
StrainFacts-0.4.0b0.dist-info/LICENSE
StrainFacts-0.4.0b0.dist-info/METADATA
StrainFacts-0.4.0b0.dist-info/WHEEL
StrainFacts-0.4.0b0.dist-info/entry_points.txt
StrainFacts-0.4.0b0.dist-info/top_level.txt
StrainFacts-0.4.0b0.dist-info/RECORD
