Metadata-Version: 2.1
Name: StrainFacts
Version: 0.4.0b0
Summary: Factorize metagenotypes to infer strains and their abundances
Home-page: http://github.com/bsmith89/StrainFacts
Author: Byron J. Smith
Author-email: me@byronjsmith.com
License-File: LICENSE
Requires-Dist: torch (>=1.0)
Requires-Dist: pyro-ppl (>=1.8)
Requires-Dist: xarray (>=2022.0)
Requires-Dist: netcdf4 (>=1.0)
Requires-Dist: pandas (>=1.0)
Requires-Dist: matplotlib (>=3.0)
Requires-Dist: numpy (>=1.0)
Requires-Dist: scipy (>=1.0)
Requires-Dist: tqdm (>=4.0)
Requires-Dist: scikit-learn (>=1.0)
Requires-Dist: seaborn (>=0.12)
